{
  "version": 2,
  "projects": {
    "demo": {
      "projectType": "application",
      "root": "apps/demo",
      "sourceRoot": "apps/demo/src",
      "prefix": "modal-routes",
      "targets": {
        "build": {
          "executor": "@angular-devkit/build-angular:browser",
          "options": {
            "outputPath": "dist/apps/demo",
            "index": "apps/demo/src/index.html",
            "main": "apps/demo/src/main.ts",
            "polyfills": "apps/demo/src/polyfills.ts",
            "tsConfig": "apps/demo/tsconfig.app.json",
            "aot": true,
            "assets": [
              "apps/demo/src/assets",
              {
                "glob": "**/*.svg",
                "input": "node_modules/ionicons/dist/ionicons/svg",
                "output": "./svg"
              }
            ],
            "styles": [
              "apps/demo/src/styles.scss",
              {
                "input": "apps/demo/src/theme/variables.scss"
              }
            ],
            "scripts": []
          },
          "configurations": {
            "production": {
              "fileReplacements": [
                {
                  "replace": "apps/demo/src/environments/environment.ts",
                  "with": "apps/demo/src/environments/environment.prod.ts"
                }
              ],
              "optimization": true,
              "outputHashing": "all",
              "sourceMap": false,
              "namedChunks": false,
              "extractLicenses": true,
              "vendorChunk": false,
              "buildOptimizer": true,
              "budgets": [
                {
                  "type": "initial",
                  "maximumWarning": "2mb",
                  "maximumError": "5mb"
                },
                {
                  "type": "anyComponentStyle",
                  "maximumWarning": "6kb",
                  "maximumError": "10kb"
                }
              ]
            }
          }
        },
        "serve": {
          "executor": "@angular-devkit/build-angular:dev-server",
          "options": {
            "browserTarget": "demo:build"
          },
          "configurations": {
            "production": {
              "browserTarget": "demo:build:production"
            }
          }
        },
        "extract-i18n": {
          "executor": "@angular-devkit/build-angular:extract-i18n",
          "options": {
            "browserTarget": "demo:build"
          }
        },
        "lint": {
          "executor": "@nrwl/linter:eslint",
          "options": {
            "lintFilePatterns": [
              "apps/demo/src/**/*.ts",
              "apps/demo/src/**/*.html"
            ]
          }
        },
        "test": {
          "executor": "@nrwl/jest:jest",
          "outputs": [
            "coverage/apps/demo"
          ],
          "options": {
            "jestConfig": "apps/demo/jest.config.js",
            "passWithNoTests": true
          }
        },
        "cap": {
          "executor": "@nxtend/capacitor:cap",
          "options": {
            "cmd": "--help"
          }
        },
        "add": {
          "executor": "@nxtend/capacitor:cap",
          "options": {
            "cmd": "add",
            "packageInstall": true
          },
          "configurations": {
            "ios": {
              "cmd": "add ios"
            },
            "android": {
              "cmd": "add android"
            }
          }
        },
        "copy": {
          "executor": "@nxtend/capacitor:cap",
          "options": {
            "cmd": "copy",
            "packageInstall": false
          },
          "configurations": {
            "ios": {
              "cmd": "copy ios"
            },
            "android": {
              "cmd": "copy android"
            }
          }
        },
        "open": {
          "executor": "@nxtend/capacitor:cap",
          "options": {
            "cmd": "open",
            "packageInstall": false
          },
          "configurations": {
            "ios": {
              "cmd": "open ios"
            },
            "android": {
              "cmd": "open android"
            }
          }
        },
        "sync": {
          "executor": "@nxtend/capacitor:cap",
          "options": {
            "cmd": "sync",
            "packageInstall": true
          },
          "configurations": {
            "ios": {
              "cmd": "sync ios"
            },
            "android": {
              "cmd": "sync android"
            }
          }
        },
        "update": {
          "executor": "@nxtend/capacitor:cap",
          "options": {
            "cmd": "update",
            "packageInstall": true
          },
          "configurations": {
            "ios": {
              "cmd": "update ios"
            },
            "android": {
              "cmd": "update android"
            }
          }
        }
      }
    },
    "demo-e2e": {
      "root": "apps/demo-e2e",
      "sourceRoot": "apps/demo-e2e/src",
      "projectType": "application",
      "targets": {
        "e2e": {
          "executor": "@nrwl/cypress:cypress",
          "options": {
            "cypressConfig": "apps/demo-e2e/cypress.json",
            "tsConfig": "apps/demo-e2e/tsconfig.e2e.json",
            "devServerTarget": "demo:serve"
          },
          "configurations": {
            "production": {
              "devServerTarget": "demo:serve:production"
            }
          }
        },
        "lint": {
          "executor": "@nrwl/linter:eslint",
          "options": {
            "lintFilePatterns": [
              "apps/demo-e2e/**/*.{js,ts}"
            ]
          }
        }
      }
    },
    "sub-routes": {
      "projectType": "library",
      "root": "libs/sub-routes",
      "sourceRoot": "libs/sub-routes/src",
      "prefix": "modal-routes",
      "targets": {
        "lint": {
          "executor": "@nrwl/linter:eslint",
          "options": {
            "lintFilePatterns": [
              "libs/sub-routes/src/**/*.ts",
              "libs/sub-routes/src/**/*.html"
            ]
          }
        },
        "test": {
          "executor": "@nrwl/jest:jest",
          "outputs": [
            "coverage/libs/sub-routes"
          ],
          "options": {
            "jestConfig": "libs/sub-routes/jest.config.js",
            "passWithNoTests": true
          }
        }
      }
    }
  },
  "cli": {
    "defaultCollection": "@nxtend/ionic-angular"
  },
  "generators": {
    "@nrwl/angular:application": {
      "style": "scss",
      "linter": "eslint",
      "unitTestRunner": "jest",
      "e2eTestRunner": "cypress"
    },
    "@nrwl/angular:library": {
      "style": "scss",
      "linter": "eslint",
      "unitTestRunner": "jest"
    },
    "@nrwl/angular:component": {
      "style": "scss"
    }
  },
  "defaultProject": "demo"
}
